{
  "name": "Eight of Pentacles",
  "name_pl": "Ósemka Monet",
  "description": "A figure diligently working on carving eight pentacles, often depicted in a workshop, symbolizing hard work, skill development, and dedication.",
  "description_pl": "Postać pilnie pracująca nad rzeźbieniem ośmiu pentakli, często przedstawiana w warsztacie, symbolizująca ciężką pracę, rozwój umiejętności i poświęcenie.",
  "upright_meaning": "Skill development, hard work, and dedication.",
  "upright_meaning_pl": "Rozwój umiejętności, ciężka praca i poświęcenie.",
  "reversed_meaning": "Lack of focus, poor quality, and shortcuts.",
  "reversed_meaning_pl": "Brak skupienia, niska jakość i pójście na skróty.",
  "significator_type": "Represents material aspects, work, and finances.",
  "significator_type_pl": "Reprezentuje aspekty materialne, pracę i finanse."
}
